LICENSE.txt
README.rst
setup.py
ANGIE3D_pyuse/__init__.py
ANGIE3D_pyuse/fluxE.py
ANGIE3D_pyuse.egg-info/PKG-INFO
ANGIE3D_pyuse.egg-info/SOURCES.txt
ANGIE3D_pyuse.egg-info/dependency_links.txt
ANGIE3D_pyuse.egg-info/top_level.txt